titato/__init__.py
titato/setting.py
titato/client/__init__.py
titato/client/console.py
titato/core/__init__.py
titato/core/game/__init__.py
titato/core/game/ai.py
titato/core/game/cheker.py
titato/core/game/game_xo.py
titato/core/game/result.py
titato/core/player/__init__.py
titato/core/player/player.py
titato/core/player/players.py
titato/core/player/symbol.py
titato/core/table/__init__.py
titato/core/table/annotations.py
titato/core/table/cell.py
titato/core/table/combinations.py
titato/core/table/param.py
titato/core/table/table.py
titato/exceptions/__init__.py
titato/exceptions/core_exceptions.py
titato-1.0.1.dist-info/METADATA
titato-1.0.1.dist-info/WHEEL
titato-1.0.1.dist-info/licenses/LICENSE.md
titato-1.0.1.dist-info/RECORD
