Metadata-Version: 2.1
Name: titato
Version: 1.0.1
Summary: Library of the game tic-tac-toe + AI. Experimental functionality with dynamic parameters of the game field
Project-URL: Documentation, https://github.com/Steppe-Mammoth/titato/tree/dev-1.x#titato
Project-URL: Source, https://github.com/Steppe-Mammoth/titato/tree/dev-1.x
Project-URL: Issues, https://github.com/Steppe-Mammoth/titato/issues
Author-email: Steppe_Mammoth <qwqwqww404@gmail.com>
License-File: LICENSE.md
Keywords: api,framework,game,tic-tac-toe
Classifier: Development Status :: 5 - Production/Stable
Classifier: License :: OSI Approved :: MIT License
Classifier: Operating System :: OS Independent
Classifier: Programming Language :: Python
Classifier: Programming Language :: Python :: 3
Classifier: Programming Language :: Python :: 3.10
Classifier: Programming Language :: Python :: 3.11
Classifier: Topic :: Games/Entertainment
Requires-Python: >=3.10
Requires-Dist: prettytable~=3.6.0
